exchangeratesapi/__init__.py
exchangeratesapi/api.py
python_exchangeratesapi-0.0.1.dist-info/LICENSE
python_exchangeratesapi-0.0.1.dist-info/METADATA
python_exchangeratesapi-0.0.1.dist-info/WHEEL
python_exchangeratesapi-0.0.1.dist-info/top_level.txt
python_exchangeratesapi-0.0.1.dist-info/RECORD
