Metadata-Version: 2.1
Name: python-exchangeratesapi
Version: 0.0.1
Summary: Simple python api wrapper for exchangeratesapi.io
Home-page: https://github.com/dclimber/python-exchangeratesapi
Author: Dastan Abdrakhmanov
Author-email: dastand.climber@gmail.com
License: UNKNOWN
Platform: UNKNOWN
Classifier: Programming Language :: Python :: 3
Classifier: License :: OSI Approved :: MIT License
Classifier: Operating System :: OS Independent
Requires-Python: >=3.5
Requires-Dist: requests
